sphinx_needs_tree_map/__init__.py
sphinx_needs_tree_map/directives/__init__.py
sphinx_needs_tree_map/directives/needtreemap.py
sphinx_needs_tree_map/static/needtreemap.css
sphinx_needs_tree_map/templates/treemap.html.jinja2
sphinx_needs_tree_map/utils/__init__.py
sphinx_needs_tree_map/utils/filters.py
sphinx_needs_tree_map/utils/hierarchy.py
sphinx_needs_tree_map/utils/plotly_renderer.py
sphinx_needs_tree_map-0.1.0.dist-info/METADATA
sphinx_needs_tree_map-0.1.0.dist-info/WHEEL
sphinx_needs_tree_map-0.1.0.dist-info/licenses/LICENSE
sphinx_needs_tree_map-0.1.0.dist-info/RECORD
