Metadata-Version: 2.4
Name: sphinx-needs-tree-map
Version: 0.1.0
Summary: StrictDoc-style tree map visualizations for sphinx-needs
Project-URL: Homepage, https://github.com/patdhlk/sphinx-needs-tree-map
Project-URL: Documentation, https://patdhlk.github.io/sphinx-needs-tree-map
Project-URL: Repository, https://github.com/patdhlk/sphinx-needs-tree-map
Project-URL: Issues, https://github.com/patdhlk/sphinx-needs-tree-map/issues
Project-URL: Changelog, https://github.com/patdhlk/sphinx-needs-tree-map/blob/main/CHANGELOG.md
Author: patdhlk
License-Expression: MIT
License-File: LICENSE
Keywords: documentation,plotly,requirements,sphinx,sphinx-needs,treemap,visualization
Classifier: Development Status :: 3 - Alpha
Classifier: Framework :: Sphinx
Classifier: Framework :: Sphinx :: Extension
Classifier: Intended Audience :: Developers
Classifier: License :: OSI Approved :: MIT License
Classifier: Operating System :: OS Independent
Classifier: Programming Language :: Python :: 3
Classifier: Programming Language :: Python :: 3.9
Classifier: Programming Language :: Python :: 3.10
Classifier: Programming Language :: Python :: 3.11
Classifier: Programming Language :: Python :: 3.12
Classifier: Programming Language :: Python :: 3.13
Classifier: Topic :: Documentation
Classifier: Topic :: Documentation :: Sphinx
Classifier: Topic :: Software Development :: Documentation
Classifier: Typing :: Typed
Requires-Python: >=3.9
Requires-Dist: jinja2>=3.0
Requires-Dist: sphinx-needs>=4.1.0
Requires-Dist: sphinx<9.0,>=5.0
Provides-Extra: dev
Requires-Dist: mypy>=1.0; extra == 'dev'
Requires-Dist: pre-commit>=3.0; extra == 'dev'
Requires-Dist: pytest-cov>=4.0; extra == 'dev'
Requires-Dist: pytest>=7.0; extra == 'dev'
Requires-Dist: ruff>=0.1.0; extra == 'dev'
Provides-Extra: docs
Requires-Dist: furo>=2024.1.0; extra == 'docs'
Requires-Dist: myst-parser>=2.0; extra == 'docs'
Requires-Dist: sphinx-autodoc-typehints>=2.0; extra == 'docs'
Requires-Dist: sphinx-copybutton>=0.5; extra == 'docs'
Requires-Dist: sphinx-design>=0.5; extra == 'docs'
